CHANGELOG
LICENSE
MANIFEST.in
README.md
requirements-dev.txt
requirements-performance.txt
requirements.txt
setup.py
aiotasks/__init__.py
aiotasks/__main__.py
aiotasks.egg-info/PKG-INFO
aiotasks.egg-info/SOURCES.txt
aiotasks.egg-info/dependency_links.txt
aiotasks.egg-info/entry_points.txt
aiotasks.egg-info/requires.txt
aiotasks.egg-info/top_level.txt
aiotasks/actions/__init__.py
aiotasks/actions/helpers.py
aiotasks/actions/default/__init__.py
aiotasks/actions/default/api.py
aiotasks/actions/default/cli.py
aiotasks/actions/default/console.py
aiotasks/actions/default/model.py
aiotasks/core/__init__.py
aiotasks/core/exceptions.py
aiotasks/core/helpers.py
aiotasks/core/logger.py
aiotasks/core/model.py
aiotasks/core/shared_cmd_options.py
aiotasks/helpers/__init__.py
aiotasks/tasks/__init__.py
aiotasks/tasks/backends.py
aiotasks/tasks/bases.py
aiotasks/tasks/context.py
aiotasks/tasks/memory.py
aiotasks/tasks/redis.py
examples/__init__.py
examples/memory_backend/__init__.py
examples/memory_backend/basic_delay.py
examples/memory_backend/basic_subcribers.py
examples/memory_backend/basic_wait.py
examples/redis_backend/__init__.py
examples/redis_backend/basic_delay.py
examples/redis_backend/basic_delay_blah.py
examples/redis_backend/basic_subcribers.py
examples/redis_backend/basic_wait.py
examples/redis_backend/current_app/__init__.py
examples/redis_backend/current_app/main.py
examples/redis_backend/current_app/subapp.py
examples/run_executable_redis/__init__.py
examples/run_executable_redis/basic_delay.py
examples/run_executable_redis/basic_subcribers.py
examples/run_executable_redis/basic_wait.py
tests/__init__.py
tests/unittesting/__init__.py
tests/unittesting/actions/__init__.py
tests/unittesting/actions/default/__init__.py
tests/unittesting/actions/default/api/__init__.py
tests/unittesting/actions/default/api/test_run_aiotasks.py
tests/unittesting/actions/default/cli/__init__.py
tests/unittesting/actions/default/cli/test_cli.py
tests/unittesting/actions/default/cli/test_cli_info.py
tests/unittesting/core/__init__.py
tests/unittesting/core/helpers/__init__.py
tests/unittesting/core/helpers/test_dict_to_obj.py
tests/unittesting/core/logger/__init__.py
